[
    {
        "topic": "Documentation",
        "id": "api",
        "items": [
            {
                "topic": "Lazo Controller",
                "link": "LazoController"
            },
            {
                "topic": "Lazo Collection",
                "link": "LazoCollection"
            },
            {
                "topic": "Lazo Model",
                "link": "LazoModel"
            },
            {
                "topic": "Lazo Syncher",
                "link": "LazoSyncher"
            },
            {
                "topic": "Service Proxy",
                "link": "ServiceProxy"
            }
        ]
    }
]
